<?xml version="1.0" encoding="UTF-8" standalone="no"?>
<c:changelog project="com.io7m.exfilac" xmlns:c="urn:com.io7m.changelog:4.0">
  <c:releases>
    <c:release date="2024-09-19T00:00:00+00:00" is-open="false" ticket-system="com.github.io7m.exfilac" version="1.0.0-beta0001">
      <c:changes/>
    </c:release>
    <c:release date="2024-09-19T00:00:00+00:00" is-open="false" ticket-system="com.github.io7m.exfilac" version="1.0.0-beta0002">
      <c:changes/>
    </c:release>
    <c:release date="2024-09-19T00:00:00+00:00" is-open="false" ticket-system="com.github.io7m.exfilac" version="1.0.0-beta0003">
      <c:changes/>
    </c:release>
    <c:release date="2024-09-20T00:00:00+00:00" is-open="false" ticket-system="com.github.io7m.exfilac" version="1.0.0-beta0004">
      <c:changes/>
    </c:release>
    <c:release date="2024-09-20T00:00:00+00:00" is-open="false" ticket-system="com.github.io7m.exfilac" version="1.0.0-beta0005">
      <c:changes/>
    </c:release>
    <c:release date="2024-09-20T00:00:00+00:00" is-open="false" ticket-system="com.github.io7m.exfilac" version="1.0.0-beta0006">
      <c:changes/>
    </c:release>
    <c:release date="2024-09-20T00:00:00+00:00" is-open="false" ticket-system="com.github.io7m.exfilac" version="1.0.0-beta0007">
      <c:changes/>
    </c:release>
    <c:release date="2024-09-20T00:00:00+00:00" is-open="false" ticket-system="com.github.io7m.exfilac" version="1.0.0">
      <c:changes/>
    </c:release>
    <c:release date="2024-09-21T00:00:00+00:00" is-open="false" ticket-system="com.github.io7m.exfilac" version="1.0.1">
      <c:changes>
        <c:change date="2024-09-21T00:00:00+00:00" summary="Adjust build process."/>
      </c:changes>
    </c:release>
    <c:release date="2024-09-24T15:30:35+00:00" is-open="false" ticket-system="com.github.io7m.exfilac" version="1.0.3">
      <c:changes>
        <c:change date="2024-09-24T00:00:00+00:00" summary="Adjust build process for F-Droid."/>
      </c:changes>
    </c:release>
  </c:releases>
  <c:ticket-systems>
    <c:ticket-system default="true" id="com.github.io7m.exfilac" url="https://www.github.com/io7m-com/exfilac/issues/"/>
  </c:ticket-systems>
</c:changelog>
